pybdc/__init__.py
pybdc/client.py
pybdc/settings.py
pybdc/utils.py
pybdc-1.1.0.dist-info/METADATA
pybdc-1.1.0.dist-info/WHEEL
pybdc-1.1.0.dist-info/top_level.txt
pybdc-1.1.0.dist-info/RECORD
