Metadata-Version: 2.1
Name: pybdc
Version: 1.1.0
Summary: UNKNOWN
Home-page: https://github.com/WongHungching/pybdc.git
Author: WongHungching
Author-email: 249768447@qq.com
License: UNKNOWN
Platform: UNKNOWN
Requires-Dist: requests
